{
    "swagger": "2.0",
    "info": {
        "description": "Registration and interaction with post`s",
        "title": "Registration",
        "contact": {},
        "version": "1.0"
    },
    "host": "localhost:8080",
    "basePath": "/",
    "paths": {
        "/API/create_post": {
            "post": {
                "description": "create post",
                "consumes": [
                    "application/json"
                ],
                "produces": [
                    "application/json"
                ],
                "tags": [
                    "API"
                ],
                "summary": "CreatePost",
                "operationId": "create-post",
                "parameters": [
                    {
                        "description": "post info",
                        "name": "input",
                        "in": "body",
                        "required": true,
                        "schema": {
                            "$ref": "#/definitions/pkg_api.PostInput"
                        }
                    }
                ],
                "responses": {
                    "200": {
                        "description": "OK",
                        "schema": {
                            "type": "object",
                            "additionalProperties": true
                        }
                    },
                    "400": {
                        "description": "Bad Request",
                        "schema": {
                            "type": "object",
                            "additionalProperties": true
                        }
                    },
                    "401": {
                        "description": "Unauthorized",
                        "schema": {
                            "type": "object",
                            "additionalProperties": true
                        }
                    }
                }
            }
        },
        "/API/delete_post": {
            "delete": {
                "description": "delete post",
                "consumes": [
                    "application/json"
                ],
                "produces": [
                    "application/json"
                ],
                "tags": [
                    "API"
                ],
                "summary": "UpdatePost",
                "operationId": "delete-post",
                "parameters": [
                    {
                        "description": "post id",
                        "name": "input",
                        "in": "body",
                        "required": true,
                        "schema": {
                            "$ref": "#/definitions/pkg_api.PostInput"
                        }
                    }
                ],
                "responses": {
                    "200": {
                        "description": "post deleted",
                        "schema": {
                            "type": "object",
                            "additionalProperties": true
                        }
                    },
                    "400": {
                        "description": "Bad Request",
                        "schema": {
                            "type": "object",
                            "additionalProperties": true
                        }
                    },
                    "401": {
                        "description": "Unauthorized",
                        "schema": {
                            "type": "object",
                            "additionalProperties": true
                        }
                    }
                }
            }
        },
        "/API/profile": {
            "get": {
                "description": "user profile",
                "produces": [
                    "application/json"
                ],
                "tags": [
                    "API"
                ],
                "summary": "SignIn",
                "operationId": "get-profile",
                "responses": {
                    "200": {
                        "description": "OK",
                        "schema": {
                            "$ref": "#/definitions/db.User"
                        }
                    },
                    "400": {
                        "description": "Bad Request",
                        "schema": {
                            "type": "object",
                            "additionalProperties": true
                        }
                    },
                    "401": {
                        "description": "Unauthorized",
                        "schema": {
                            "type": "object",
                            "additionalProperties": true
                        }
                    }
                }
            }
        },
        "/API/update_post": {
            "patch": {
                "description": "update post",
                "consumes": [
                    "application/json"
                ],
                "produces": [
                    "application/json"
                ],
                "tags": [
                    "API"
                ],
                "summary": "UpdatePost",
                "operationId": "update-post",
                "parameters": [
                    {
                        "description": "post info",
                        "name": "input",
                        "in": "body",
                        "required": true,
                        "schema": {
                            "$ref": "#/definitions/pkg_api.PostInput"
                        }
                    }
                ],
                "responses": {
                    "200": {
                        "description": "post updated",
                        "schema": {
                            "type": "object",
                            "additionalProperties": true
                        }
                    },
                    "400": {
                        "description": "Bad Request",
                        "schema": {
                            "type": "object",
                            "additionalProperties": true
                        }
                    },
                    "401": {
                        "description": "Unauthorized",
                        "schema": {
                            "type": "object",
                            "additionalProperties": true
                        }
                    }
                }
            }
        },
        "/auth/sign-in": {
            "post": {
                "description": "sing-in",
                "consumes": [
                    "application/json"
                ],
                "produces": [
                    "application/json"
                ],
                "tags": [
                    "auth"
                ],
                "summary": "SignIn",
                "operationId": "sing-in",
                "parameters": [
                    {
                        "description": "credentials",
                        "name": "input",
                        "in": "body",
                        "required": true,
                        "schema": {
                            "$ref": "#/definitions/pkg_api.signInInput"
                        }
                    }
                ],
                "responses": {
                    "200": {
                        "description": "token",
                        "schema": {
                            "type": "object",
                            "additionalProperties": true
                        }
                    },
                    "400": {
                        "description": "Bad Request",
                        "schema": {
                            "type": "object",
                            "additionalProperties": true
                        }
                    }
                }
            }
        },
        "/auth/sign-up": {
            "post": {
                "description": "create account",
                "consumes": [
                    "application/json"
                ],
                "produces": [
                    "application/json"
                ],
                "tags": [
                    "auth"
                ],
                "summary": "SignUp",
                "operationId": "sing-up",
                "parameters": [
                    {
                        "description": "account info",
                        "name": "input",
                        "in": "body",
                        "required": true,
                        "schema": {
                            "$ref": "#/definitions/pkg_api.signUpInput"
                        }
                    }
                ],
                "responses": {
                    "200": {
                        "description": "token",
                        "schema": {
                            "type": "object",
                            "additionalProperties": true
                        }
                    },
                    "400": {
                        "description": "Bad Request",
                        "schema": {
                            "type": "object",
                            "additionalProperties": true
                        }
                    },
                    "401": {
                        "description": "Unauthorized",
                        "schema": {
                            "type": "object",
                            "additionalProperties": true
                        }
                    }
                }
            }
        }
    },
    "definitions": {
        "db.Post": {
            "type": "object",
            "properties": {
                "createdAt": {
                    "type": "string"
                },
                "deletedAt": {
                    "$ref": "#/definitions/gorm.DeletedAt"
                },
                "description": {
                    "type": "string"
                },
                "id": {
                    "type": "integer"
                },
                "image": {
                    "type": "string"
                },
                "title": {
                    "type": "string"
                },
                "updatedAt": {
                    "type": "string"
                },
                "users": {
                    "type": "array",
                    "items": {
                        "$ref": "#/definitions/db.User"
                    }
                }
            }
        },
        "db.User": {
            "type": "object",
            "properties": {
                "createdAt": {
                    "type": "string"
                },
                "deletedAt": {
                    "$ref": "#/definitions/gorm.DeletedAt"
                },
                "email": {
                    "type": "string"
                },
                "id": {
                    "type": "integer"
                },
                "name": {
                    "type": "string"
                },
                "posts": {
                    "type": "array",
                    "items": {
                        "$ref": "#/definitions/db.Post"
                    }
                },
                "updatedAt": {
                    "type": "string"
                }
            }
        },
        "github.com_StepanShevelev_registration_pkg_api.PostInput": {
            "type": "object",
            "properties": {
                "description": {
                    "type": "string"
                },
                "id": {
                    "type": "integer"
                },
                "image": {
                    "type": "string"
                },
                "title": {
                    "type": "string"
                }
            }
        },
        "github.com_StepanShevelev_registration_pkg_api.signInInput": {
            "type": "object",
            "properties": {
                "email": {
                    "type": "string"
                },
                "password": {
                    "type": "string"
                }
            }
        },
        "github.com_StepanShevelev_registration_pkg_api.signUpInput": {
            "type": "object",
            "required": [
                "email",
                "name",
                "password",
                "password_confirm"
            ],
            "properties": {
                "email": {
                    "type": "string"
                },
                "name": {
                    "type": "string"
                },
                "password": {
                    "type": "string"
                },
                "password_confirm": {
                    "type": "string"
                }
            }
        },
        "gorm.DeletedAt": {
            "type": "object",
            "properties": {
                "time": {
                    "type": "string"
                },
                "valid": {
                    "description": "Valid is true if Time is not NULL",
                    "type": "boolean"
                }
            }
        },
        "pkg_api.PostInput": {
            "type": "object",
            "properties": {
                "description": {
                    "type": "string"
                },
                "id": {
                    "type": "integer"
                },
                "image": {
                    "type": "string"
                },
                "title": {
                    "type": "string"
                }
            }
        },
        "pkg_api.signInInput": {
            "type": "object",
            "properties": {
                "email": {
                    "type": "string"
                },
                "password": {
                    "type": "string"
                }
            }
        },
        "pkg_api.signUpInput": {
            "type": "object",
            "required": [
                "email",
                "name",
                "password",
                "password_confirm"
            ],
            "properties": {
                "email": {
                    "type": "string"
                },
                "name": {
                    "type": "string"
                },
                "password": {
                    "type": "string"
                },
                "password_confirm": {
                    "type": "string"
                }
            }
        }
    },
    "securityDefinitions": {
        "ApiKeyAuth": {
            "type": "apiKey",
            "name": "Authorization",
            "in": "header"
        }
    }
}